README.md
setup.py
redisbeat/__init__.py
redisbeat/scheduler.py
redisbeat.egg-info/PKG-INFO
redisbeat.egg-info/SOURCES.txt
redisbeat.egg-info/dependency_links.txt
redisbeat.egg-info/requires.txt
redisbeat.egg-info/top_level.txt