Metadata-Version: 1.1
Name: redisbeat
Version: 1.2.6
Summary: Redis Scheduler For Celery, Support Add Task Dynamic
Home-page: https://liqiang.io/opensources/redisbeat
Author: Liqiang Liu
Author-email: liqianglau@outlook.com
License: MIT
Keywords: celery scheduler redis beat
Platform: UNKNOWN
Classifier: Development Status :: 3 - Alpha
Classifier: Intended Audience :: Developers
Classifier: Topic :: Software Development :: Libraries
Classifier: License :: OSI Approved :: MIT License
Classifier: Programming Language :: Python :: 2
Classifier: Programming Language :: Python :: 2.7
Classifier: Programming Language :: Python :: 3
Classifier: Programming Language :: Python :: 3.5
